pysilsub/.DS_Store
pysilsub/CIE.py
pysilsub/__init__.py
pysilsub/asano.py
pysilsub/binocular.py
pysilsub/colorfunc.py
pysilsub/config.py
pysilsub/device.py
pysilsub/exceptions.py
pysilsub/plotting.py
pysilsub/precep.py
pysilsub/problem.py
pysilsub/stimfun.py
pysilsub/utils.py
pysilsub/data/.DS_Store
pysilsub/data/BCGAR.csv
pysilsub/data/BCGAR.json
pysilsub/data/LEDCube.csv
pysilsub/data/LEDCube.json
pysilsub/data/OneLight.csv
pysilsub/data/OneLight.json
pysilsub/data/STLAB_1_York.csv
pysilsub/data/STLAB_1_York.json
pysilsub/data/STLAB_2_York.csv
pysilsub/data/STLAB_2_York.json
pysilsub/data/STLAB_Oxford.csv
pysilsub/data/STLAB_Oxford.json
pysilsub/data/VirtualSky.csv
pysilsub/data/VirtualSky.json
pysilsub-0.0.13.dist-info/LICENSE
pysilsub-0.0.13.dist-info/METADATA
pysilsub-0.0.13.dist-info/WHEEL
pysilsub-0.0.13.dist-info/top_level.txt
pysilsub-0.0.13.dist-info/RECORD
