Metadata-Version: 2.1
Name: pysilsub
Version: 0.0.13
Summary: Software for performing silent substitution in Python.
Home-page: https://github.com/PySilentSubstitution/pysilsub
Author: Joel T. Martin
Author-email: joel.t.martin36@gmail.com
License: MIT
Project-URL: Documentation, https://pysilentsubstitution.github.io/pysilsub/index.html
Keywords: silent substitution,vision,psychology,perception,metamer,spectra,LED
Classifier: Development Status :: 2 - Pre-Alpha
Classifier: Topic :: Scientific/Engineering :: Information Analysis
Classifier: License :: OSI Approved :: MIT License
Classifier: Intended Audience :: Science/Research
Classifier: Programming Language :: Python :: 3.7
Requires-Python: >=3.8, <3.11
License-File: LICENSE
Requires-Dist: numpy
Requires-Dist: scipy
Requires-Dist: matplotlib
Requires-Dist: seaborn
Requires-Dist: pandas
Requires-Dist: importlib-resources
Requires-Dist: colour-science
